tools_lyc7456/__init__.py
tools_lyc7456/aliCloud/__init__.py
tools_lyc7456/aliCloud/swas.py
tools_lyc7456/baiduCloud/__init__.py
tools_lyc7456/baiduCloud/bos.py
tools_lyc7456/baiduCloud/sms.py
tools_lyc7456/public/__init__.py
tools_lyc7456/public/db.py
tools_lyc7456/public/directory.py
tools_lyc7456/public/ftp.py
tools_lyc7456/public/log.py
tools_lyc7456/public/md5sum.py
tools_lyc7456/public/public.py
tools_lyc7456/public/ssh.py
tools_lyc7456/public/timestamp.py
tools_lyc7456/public/webhook_bot.py
tools_lyc7456/public/wrapper.py
tools_lyc7456/qCloud/__init__.py
tools_lyc7456/qCloud/cvm.py
tools_lyc7456/qCloud/dnspod.py
tools_lyc7456/qCloud/vpc.py
tools_lyc7456/uCloud/__init__.py
tools_lyc7456/uCloud/us3.py
tools_lyc7456/uCloudapi/__init__.py
tools_lyc7456/uCloudapi/signature.py
tools_lyc7456/uCloudapi/udb.py
tools_lyc7456/uCloudapi/uhost.py
tools_lyc7456/uCloudapi/uvpc.py
tools_lyc7456-0.0.38.dist-info/LICENSE
tools_lyc7456-0.0.38.dist-info/METADATA
tools_lyc7456-0.0.38.dist-info/WHEEL
tools_lyc7456-0.0.38.dist-info/top_level.txt
tools_lyc7456-0.0.38.dist-info/RECORD
