Metadata-Version: 2.1
Name: tools-lyc7456
Version: 0.0.38
Summary: lyc7456 运维开发小工具
Home-page: https://gitee.com/lyc7456/tools-lyc7456.git
Author: lyc7456
Author-email: lyc7456gg1@gmail.com
Classifier: Programming Language :: Python :: 3.6
Classifier: Programming Language :: Python :: 3.7
Classifier: Programming Language :: Python :: 3.8
Classifier: Programming Language :: Python :: 3.9
Classifier: License :: OSI Approved :: MIT License
Classifier: Operating System :: OS Independent
Requires-Python: >=3.6
License-File: LICENSE
Requires-Dist: requests
Requires-Dist: bce-python-sdk (>=0.8.61)
Requires-Dist: ucloud-sdk-python3
Requires-Dist: tencentcloud-sdk-python
Requires-Dist: paramiko (==2.7.1)
Requires-Dist: alibabacloud-swas-open20200601 (==1.0.2)
